{
    "esModuleInterop": true,
    "module": "esnext",
    "moduleResolution": "node",
    "resolveJsonModule": true,
    "isolatedModules": true,
    "jsx": "preserve",
    "incremental": true,
      "@templates": ["./@next/components/templates"],
      "@pages": ["./@next/pages"],
      "@layouts": ["./@next/layouts"]
    }
   "powerReduction": 1000000,
    "dynamicLink": {
      "baseURL": "https://pylons.page.link",
      "apn": "tech.pylons.wallet",
      "ibi": "xyz.pylons.wallet",
      "isi": "1598732789",
      "oflPlay": "https://play.google.com/store/apps/details?id=tech.pylons.wallet&pcampaignid=pcampaignidMKT-Other-global-all-co-prtnr-py-PartBadge-Mar2515-1",
      "oflIOS": "https://apps.apple.com/us/app/pylons/id1598732789"
    },
    "coins": [
      {
        "denom": "uatom",
        "displayName": "ATOM",
        "fraction": 1000000
      },
